<?xml version="1.0" encoding="UTF-8"?>
<site id="13213">
  <description>
    <author>Adam Dixon</author>
    <date>2024-03-15</date>
    <dataset>GEOID_13213_Georgia</dataset>
  </description>
  <soil>
    <general usehistory="arable" humus="HUMUS" soil="LOAM"/>
    <layers>
      <layer  wcmin="97.4216361081819" wcmax="234.385511373373" ph="5.02288898468018" corg="0.0189944444444444" clay="0.158088888888889" sand="0.391024444124434" bd="1.38347778439522" depth="2" sks="0.00267943456484145"/>
      <layer  wcmin="97.4216361081819" wcmax="234.385511373373" ph="5.02288898468018" corg="0.0189944444444444" clay="0.158088888888889" sand="0.391024444124434" bd="1.38347778439522" depth="3" sks="0.00267943456484145"/>
      <layer  wcmin="97.9316878621689" wcmax="234.793591353486" ph="5.02288898468018" corg="0.0181399999750985" clay="0.158977777777778" sand="0.391028888607025" bd="1.38371111790339" depth="5" sks="0.00266090624467455"/>
      <layer  wcmin="129.760631025584" wcmax="273.719554077385" ph="5.00388899167379" corg="0.0114441110372543" clay="0.212366669040256" sand="0.329531113889482" bd="1.41298889636993" depth="10" sks="0.00133067678023418"/>
      <layer  wcmin="163.465683960887" wcmax="315.367741488965" ph="4.87950008630752" corg="0.00651961111401518" clay="0.269652777756585" sand="0.252189445002873" bd="1.3915500156747" depth="20" sks="0.000746254376274921"/>
      <layer  wcmin="164.268879587245" wcmax="326.851056989521" ph="4.24644452095032" corg="0.00319611111771729" clay="0.270432221900092" sand="0.192513332366943" bd="1.22452223433389" depth="20" sks="0.00166810954430403"/>
      <layer  wcmin="163.528701802512" wcmax="327.100431248808" ph="4.18366674105326" corg="0.00299433333733016" clay="0.269087777731154" sand="0.188254443041484" bd="1.21674445456929" depth="20" sks="0.00173234778020514"/>
      <layer  wcmin="90.3303658521869" wcmax="292.779818506833" ph="2.31811115264893" corg="0.00190233333400554" clay="0.138671111297607" sand="0.121312222798665" bd="0.653488887415992" depth="20" sks="0.0166322263059707"/>
      <layer  wcmin="86.9310965971985" wcmax="290.904911109332" ph="2.28011115339067" corg="0.0016168888895048" clay="0.132626666302151" sand="0.120387779246436" bd="0.643888888491525" depth="20" sks="0.0172820160986518"/>
      <layer  wcmin="82.6850042280222" wcmax="285.12132939303" ph="2.21811115423838" corg="0.00146177778293689" clay="0.125486666764153" sand="0.132548889541626" bd="0.628088893493017" depth="20" sks="0.018583142214309"/>
      <layer  wcmin="78.225687873746" wcmax="275.816966030379" ph="2.17944448788961" corg="0.00118477777590354" clay="0.118406666607327" sand="0.157501111274295" bd="0.618422225846185" depth="20" sks="0.0200446598999388"/>
      <layer  wcmin="71.1537983009437" wcmax="273.363480824807" ph="1.99600004090203" corg="0.000986111111607817" clay="0.105679999627007" sand="0.149628889486525" bd="0.563644446664386" depth="20" sks="0.0230080358229632"/>
      <layer  wcmin="24.1646538446233" wcmax="285.04456676698" ph="0.240555559794108" corg="0.000112777778009574" clay="0.0167777777777778" sand="0.0188544447792901" bd="0.0638666653633118" depth="20" sks="0.0561309144966276"/>
    </layers>
  </soil>
</site>
